MANIFEST.in
setup.py
swacch/__init__.py
swacch/swacch.py
swacch/version.py
swacch.egg-info/PKG-INFO
swacch.egg-info/SOURCES.txt
swacch.egg-info/dependency_links.txt
swacch.egg-info/not-zip-safe
swacch.egg-info/requires.txt
swacch.egg-info/top_level.txt
swacch/data/stopwords.json
tests/__init__.py
tests/tests_helper.py
tests/helpers/__init__.py
tests/helpers/my_helper.py
tests/unit/__init__.py
tests/unit/test_swacch.py