Metadata-Version: 1.0
Name: swacch
Version: 0.0.1
Summary: Utilities for cleaning text
Home-page: https://github.com/koustuvsinha/swacch
Author: Koustuv Sinha
Author-email: koustuvsinha@hotmail.com
License: MIT License
Keywords: text utility
Platform: UNKNOWN
